deepinspection/__init__.py
deepinspection/track/__init__.py
deepinspection/track/client.py
deepinspection-0.1.1.dist-info/METADATA
deepinspection-0.1.1.dist-info/WHEEL
deepinspection-0.1.1.dist-info/RECORD
