Metadata-Version: 2.1
Name: deepinspection
Version: 0.1.1
Summary: 
Author: NextML
Requires-Python: >=3.9,<3.11
Classifier: Programming Language :: Python :: 3
Classifier: Programming Language :: Python :: 3.9
Classifier: Programming Language :: Python :: 3.10
Requires-Dist: pydantic (>=2.6.0,<3.0.0)
Requires-Dist: requests (>=2.31.0,<3.0.0)
